{
	"info": {
		"_postman_id": "40f34184-2cf4-4f29-aec2-932632a734d5",
		"name": "collection",
		"schema": "https://schema.getpostman.com/json/collection/v2.1.0/collection.json",
		"_exporter_id": "31356996"
	},
	"item": [
		{
			"name": "get/notes",
			"request": {
				"method": "GET",
				"header": [],
				"url": {
					"raw": "http://localhost:8000/notes",
					"protocol": "http",
					"host": [
						"localhost"
					],
					"port": "8000",
					"path": [
						"notes"
					]
				}
			},
			"response": []
		},
		{
			"name": "get/UploadForms",
			"request": {
				"method": "GET",
				"header": [],
				"url": {
					"raw": "http://localhost:8000/UploadForm.html",
					"protocol": "http",
					"host": [
						"localhost"
					],
					"port": "8000",
					"path": [
						"UploadForm.html"
					]
				}
			},
			"response": []
		},
		{
			"name": "post/upload",
			"request": {
				"method": "POST",
				"header": [],
				"body": {
					"mode": "formdata",
					"formdata": []
				},
				"url": {
					"raw": "http://localhost:8000/upload",
					"protocol": "http",
					"host": [
						"localhost"
					],
					"port": "8000",
					"path": [
						"upload"
					]
				}
			},
			"response": []
		},
		{
			"name": "get/notes/:notename",
			"request": {
				"method": "GET",
				"header": [],
				"url": {
					"raw": "http://localhost:8000/notes/Dmytro",
					"protocol": "http",
					"host": [
						"localhost"
					],
					"port": "8000",
					"path": [
						"notes",
						"Dmytro"
					]
				}
			},
			"response": []
		},
		{
			"name": "put/notes",
			"request": {
				"method": "PUT",
				"header": [],
				"url": {
					"raw": "http://localhost:8000/notes/Dmytro",
					"protocol": "http",
					"host": [
						"localhost"
					],
					"port": "8000",
					"path": [
						"notes",
						"Dmytro"
					]
				}
			},
			"response": []
		},
		{
			"name": "delete/notes",
			"request": {
				"method": "DELETE",
				"header": [],
				"url": {
					"raw": "http://localhost:8000/notes/Dmytro",
					"protocol": "http",
					"host": [
						"localhost"
					],
					"port": "8000",
					"path": [
						"notes",
						"Dmytro"
					]
				}
			},
			"response": []
		}
	]
}